{
  "mp": {
    "name": "Sukhjinder Singh Randhawa",
    "constituency": "Gurdaspur",
    "state": "punjab",
    "party": "Indian National Congress",
    "myneta_candidate_id": 8728,
    "slug": "sukhjinder-singh-randhawa",
    "house": "lok_sabha",
    "sansad_member_id": 5752,
    "profile_url": null,
    "canonical_name": "Sukhjinder Singh Randhawa",
    "name_aliases": [],
    "education": "12th Pass",
    "profession": null,
    "age": 65,
    "photo_url": null
  },
  "criminal_record": {
    "total_cases": 0,
    "serious_cases": 0,
    "pending_cases": 0,
    "convictions": 0,
    "disposed_cases": 0,
    "confidence": 0.8,
    "source": "myneta"
  },
  "assets": {
    "total_assets": 71253181.0,
    "liabilities": 16132136.0,
    "movable_assets": 0,
    "immovable_assets": 0,
    "net_worth": 55121045.0,
    "confidence": 0.8,
    "source": "myneta",
    "sources": [
      {
        "url": "https://myneta.info/LokSabha2024/candidate.php?candidate_id=8728",
        "source_name": "myneta",
        "grade": "B",
        "notes": "MyNeta/ADR Lok Sabha 2024 candidate affidavit summary"
      }
    ]
  },
  "mplads": {
    "entitled": 14.7,
    "released": 14.7,
    "sanctioned": 8.42,
    "expended": 4.54,
    "source": "esakshi",
    "confidence": 0.9,
    "sources": [
      {
        "url": "https://mplads.mospi.gov.in/digigov/dashboard.html",
        "source_name": "esakshi",
        "grade": "A",
        "fetched_at": "2026-05-23T17:42:39.833825Z",
        "notes": "Official eSAKSHI REST API — Works: 281 recommended, 257 sanctioned, 56 completed"
      }
    ],
    "works": [],
    "works_count": 281,
    "esakshi_coverage_start": "2023-04-01",
    "period_data": [],
    "cumulative_entitled": null,
    "cumulative_released": null,
    "cumulative_expended": null,
    "includes_covid_suspension": false,
    "data_period_note": "",
    "utilization_rate": 30.8843537414966
  },
  "parliament_activity": {
    "attendance_percentage": 95.0,
    "questions_asked": 23,
    "debates_participated": 1,
    "private_bills_introduced": 0,
    "is_minister": false,
    "source": "prs",
    "confidence": 0.8,
    "sources": [
      {
        "url": "https://raw.githubusercontent.com/Vonter/india-representatives-activity/main/csv/Lok%20Sabha/18th.csv",
        "source_name": "prs_github_csv",
        "grade": "C",
        "fetched_at": "2026-05-21T14:24:31.317774Z",
        "notes": "PRS India GitHub CSV - 18th Lok Sabha"
      }
    ],
    "focus_topics": [],
    "notable_questions": [],
    "voting_record": []
  },
  "news_allegations": [],
  "raw_notes": "",
  "sources_consulted": [
    "prs",
    "social_media",
    "news",
    "myneta",
    "mplads"
  ],
  "collected_at": "2026-05-21T14:25:37.240408Z",
  "evidence_summary": {
    "parliament": "C",
    "accessibility": "D",
    "assets": "B",
    "criminal": "B",
    "mplads": "A"
  },
  "cag_findings": [
    {
      "report_title": "Performance Audit of MPLADS",
      "report_number": "31 of 2010",
      "year": 2010,
      "finding": "Idle funds: Rs 1,558 crore lying unspent in district authorities' accounts across states",
      "category": "idle_funds",
      "state": "national",
      "severity": "high",
      "source": {
        "url": "https://cag.gov.in/en/audit-report/details/2341",
        "source_name": "cag",
        "grade": "A",
        "fetched_at": "2026-05-21T14:25:37.254596Z",
        "notes": "CAG Report No. 31 of 2010"
      }
    },
    {
      "report_title": "Performance Audit of MPLADS",
      "report_number": "31 of 2010",
      "year": 2010,
      "finding": "Bogus utilization certificates: 34% of sampled UCs lacked proper supporting documents",
      "category": "bogus_ucs",
      "state": "national",
      "severity": "high",
      "source": {
        "url": "https://cag.gov.in/en/audit-report/details/2341",
        "source_name": "cag",
        "grade": "A",
        "fetched_at": "2026-05-21T14:25:37.254612Z",
        "notes": "CAG Report No. 31 of 2010"
      }
    },
    {
      "report_title": "Performance Audit of MPLADS",
      "report_number": "31 of 2010",
      "year": 2010,
      "finding": "Incomplete works: 18% of sampled works were abandoned or incomplete",
      "category": "incomplete_works",
      "state": "national",
      "severity": "medium",
      "source": {
        "url": "https://cag.gov.in/en/audit-report/details/2341",
        "source_name": "cag",
        "grade": "A",
        "fetched_at": "2026-05-21T14:25:37.254620Z",
        "notes": "CAG Report No. 31 of 2010"
      }
    },
    {
      "report_title": "Follow-up Audit of MPLADS",
      "report_number": "9 of 2013",
      "year": 2013,
      "finding": "Persistent idle funds: District authorities retained Rs 2,100 crore in unspent balances",
      "category": "idle_funds",
      "state": "national",
      "severity": "high",
      "source": {
        "url": "https://cag.gov.in/uploads/media/Follow-up-action-on-Audit-Report-20200902114923.pdf",
        "source_name": "cag",
        "grade": "A",
        "fetched_at": "2026-05-21T14:25:37.254627Z",
        "notes": "CAG Report No. 9 of 2013"
      }
    },
    {
      "report_title": "Performance Audit of MPLADS (2012-17)",
      "report_number": "CAG Performance Report 2017",
      "year": 2017,
      "finding": "Only 53% of recommended works completed within the audit period",
      "category": "incomplete_works",
      "state": "national",
      "severity": "medium",
      "source": {
        "url": "https://www.mplads.gov.in/MPLADS/UploadedFiles/cag%20performance%20report.pdf",
        "source_name": "cag",
        "grade": "A",
        "fetched_at": "2026-05-21T14:25:37.254635Z",
        "notes": "CAG Report No. CAG Performance Report 2017"
      }
    },
    {
      "report_title": "Performance Audit of MPLADS (2012-17)",
      "report_number": "CAG Performance Report 2017",
      "year": 2017,
      "finding": "Rs 293 crore expended on inadmissible works not covered under MPLADS guidelines",
      "category": "irregular_works",
      "state": "national",
      "severity": "high",
      "source": {
        "url": "https://www.mplads.gov.in/MPLADS/UploadedFiles/cag%20performance%20report.pdf",
        "source_name": "cag",
        "grade": "A",
        "fetched_at": "2026-05-21T14:25:37.254643Z",
        "notes": "CAG Report No. CAG Performance Report 2017"
      }
    },
    {
      "report_title": "Performance Audit of MPLADS (2012-17)",
      "report_number": "CAG Performance Report 2017",
      "year": 2017,
      "finding": "Asset registers not maintained by district authorities in 40% of sampled districts",
      "category": "poor_records",
      "state": "national",
      "severity": "medium",
      "source": {
        "url": "https://www.mplads.gov.in/MPLADS/UploadedFiles/cag%20performance%20report.pdf",
        "source_name": "cag",
        "grade": "A",
        "fetched_at": "2026-05-21T14:25:37.254649Z",
        "notes": "CAG Report No. CAG Performance Report 2017"
      }
    }
  ],
  "compensation": {
    "salary_per_month": 100000.0,
    "constituency_allowance_per_month": 70000.0,
    "office_expense_allowance_per_month": 60000.0,
    "sumptuary_allowance_per_month": 15000.0,
    "total_monthly": 245000.0,
    "total_annual": 2940000.0,
    "effective_from": "2018-04-01",
    "source_notification": "Members of Parliament (Amendment) Act, 2018; The Salary, Allowances and Pension of Members of Parliament Act, 1954 (as amended). Gazette of India, Extraordinary, Part II, Section 1.",
    "notes": "In addition to cash compensation, MPs receive non-cash perks including: free AC First Class rail travel, 34 annual air journeys, furnished office space, medical facilities at government hospitals, and housing or HRA (Rs 2,00,000/month if no government accommodation). Post-retirement pension: Rs 29,000/month (base) + Rs 1,500 per additional year served."
  },
  "sagy": [],
  "committees": {
    "memberships": [],
    "total_committees": 0,
    "leadership_roles": 0,
    "confidence": 0.0,
    "sources": []
  },
  "social_media": {
    "profiles": [],
    "total_platforms": 0,
    "total_followers": 0,
    "confidence": 0.2,
    "sources": []
  },
  "news_sentiment": {
    "total_articles": 10,
    "positive": 1,
    "negative": 0,
    "neutral": 9,
    "top_headlines": [
      {
        "headline": "Punjab govt will not survive, says Sukhjinder Singh Randhawa; SAD leader Bikram Singh Majithia says count - The Times of India",
        "source": "The Times of India",
        "severity": "low",
        "verified": false,
        "url": "https://news.google.com/rss/articles/CBMioAJBVV95cUxOZTczTXJLaVV0WGN2cFVfSUdISGhtb3FfS0ZZNWVob2xVc3NKZnN5OUhrdjVIX0xHUHZhMDA0SzVvTHNPSmxBVTNOaE9IdHo0OXg0Q19xS2Rqcnl5cTlHQzF5cXRRVHpsRXhSY05ZcUpudzExTUJLR0lBdjVBU3puVktYQWRXdkhndWdhNEpFUFFJSzd3dE9aS3R5NlFNRnVyQVpBMDlUYVR5dmxDV3BQMlJneTNKUnVqTlNNUldLLXRSVWU1dEpmakw4QlZVSFYwckxYeEgwQjJoN1RnVFc3eVMzNkVyVU9VYlhWQ2wzcmhBcE41bEU3R1M3MU01VEk5S0swQnNrLXU5QnB6aE9DYkhDX3JPLURmQlZVWlFhZTbSAaYCQVVfeXFMTm1pcjdmZWM3QUF2Tk1GX2RaLVNwNTR4Uy01NTlSQ2VZNU5jX0VScTY1WktMT25ia1laYnV4ZDF5dFhiM3U1VDEwb2puSUp4VGdweUlzWE9TdTRKaGlfVkRkOHdfYWV2Yk1QcEdQRTNJRkw3Ml9Wd3g0YTA1MFZJVzVySEMxUUx2RDQta1BsTWZXekpVeVN4R3NKU0QzVTdBRGFxVUVINUtCVi1qNFhibVAzbEw4Z2tHbXY1MjFZYVRBTG1VdFlTbnZGbG1qVDA4YVNfdE10andwbjEwYUswZXNVaWp2WmRLcXRobVhCVkw4dmFBX21WNUtWSXByQjNTRVF3ZFJURzNNYlBTQ01lSEpiS1c2Y0wzNFFqbnNRRXFrVnFfd3J3?oc=5",
        "sentiment": "neutral"
      },
      {
        "headline": "If Bhagwant Mann hadn’t become CM, he might not have remarried: Congress MP Sukhjinder Randhawa - The Tribune",
        "source": "The Tribune",
        "severity": "low",
        "verified": false,
        "url": "https://news.google.com/rss/articles/CBMizwFBVV95cUxQV2hOYkktLWtOOFlKZjNTSk5MV3YxTVBadmtuMlBIN2NMY3BpYnVVTEh0dzR2S0xTRW4tLTJvdlBCUE8zVUY2SWtlUnFMWnQzZkZsWl94ZFhvdTNMQ3RGYjUwWV9yWFN3NFJ4V3lWem80NnJRYVIxTlBUaVViOUxLOUZPODR4Q18za0tvOW5DUnFMeGNlQVBqb1FsUnN5TTFuT19NbVBVUEdyOUdTdVZQZmxncWFzUVpIMEY5enJ5Tk5kaWdSaXRucHJXS1l6ajg?oc=5",
        "sentiment": "neutral"
      },
      {
        "headline": "Punjab, land of warriors, will firmly oppose SIR irregularities: Randhawa - Cityairnews",
        "source": "Cityairnews",
        "severity": "low",
        "verified": false,
        "url": "https://news.google.com/rss/articles/CBMiqgFBVV95cUxOZm93emtNY1NwbFM5YTFtTld6WWdPVDIxei1QOUUxTzk4Uk1CZklxT1FHblVvZDVIUDVzVlNQTUR3UW14QUlVZWozNUxMZzk3b0VudHhpOW9LWjlodWhLcTFoWjNUQ2t4OVd4NzRWam1XNUZBaFFvVGRPY2k2bHpvcm1VNVltMk5DY2cyYnowbHlKZGhsMGhCdDdBTHk5NTJLbHllOUNlcmFsUQ?oc=5",
        "sentiment": "neutral"
      },
      {
        "headline": "Congress MP Sukhjinder Singh Randhawa writes to Centre complaining about Punjab DGP, chief secretary sharing ‘AAP stage’ - The Indian Express",
        "source": "The Indian Express",
        "severity": "low",
        "verified": false,
        "url": "https://news.google.com/rss/articles/CBMihwJBVV95cUxQQnZoSF9EMC1xcXAyUFh6VFA2Ymt6S3lRTmlQSnphUGVrTjkydHoycHRuSENNWUZleURRdFlHRTBMVlprLW1fTE5QTDNlN2t1TUptOUMxbVlFaE1SdE9sbDVFWWluVmEwVUJNS2wxRi1oekdTLXlOWTJuT2tzR1lyamM1ZHZybWFUOS1VNjVnN1JsRHVUWjBCbDBKdVFSWXdJZnpSRll0X2hVLVFhOElCSC1haGZKTTNoYVhVTVNHMlI2R0R1djNZVnBBbThmcEhWS1NQQVlJdS1VeGxCODQ2a0hnX1pDbTY4WEllZjZNdjZ6WEFWMmJxdTM2QllVNjdzYkJrS0NENNIBjgJBVV95cUxOSDg2Z3M0bEVHUEVUTTlMMm5yZy13S3daVms4QmlYZWxmLWdBRGpMMk9za2s4cHBuRlNFcjNwc1ZMdWp4Yk1VMHN6SzZkb3NlZW1PVHM5VFZFTlJvNFhrX3ZGNEFZdGNfcU1LR3g5NWN3aHZ5MFFnODFNTjVpOFFmN1RPSUl2YWRPZnE4SHppVTJxRmtaU1d4Y0l1Z0x1QXFXRHRzVTMzOG44WmtENmdFQjlmazZBX0VUN3NUMzItbW1ZdWhiQk1sSlpHYXhjSE5CbzVCNnY5bVBZRzhldy1hTkJudmtUdTltX2h0YWdEUXFWT0JVekN6d2dQeU80aE1zaXR2WmdHRXd0NjlPdEE?oc=5",
        "sentiment": "neutral"
      },
      {
        "headline": "It’s Centre’s gift of inflation: Randhawa - The Times of India",
        "source": "The Times of India",
        "severity": "low",
        "verified": false,
        "url": "https://news.google.com/rss/articles/CBMitwFBVV95cUxPbDNKYk12OGY2elFidEhXQjNGTkhCNDEwdGpCYzBJNDRKQjIxV0hqcm1KWjN4NEV5OVRXYWNJSmNWcl9NS2hIWGt1Nk9IVkFoUGRoTi1WNy1ua0t3ak94ZlFQcGRiYnRDM20xMk5FaG1FYmwxdG1rMlhzS1RZZUltcWZTUmtTRkkyTi0xTm1ZTkVBUVpJbHlyTTZzMkNYQTF4bGZUX1JWSU5PV3ZlNjUtdkxpcHJYWUXSAbwBQVVfeXFMTVR6Z2ZVYU16Q1pJQTgtNkxvR2QzWnlZRndCNFVYTElmbGx4S19URDJwRmhzVHk4Sl9NSHZSZ18zR1Vlbl9EVGMyODJLdGRZYXF6NjI0MXdzcmFrZ3RWb0xTSGg3X1poUzc4d01Jd2pZNWZFVEVZdDBjai1wcGZQQXlrMF9UUTRpbEFrSDg0RmtsOEUzVllpeGpDQTlON2xhblVxNnRhTzFDbUpGXzNleTRELTJDZ2tpckY4TTc?oc=5",
        "sentiment": "neutral"
      }
    ],
    "sentiment_summary": "Mixed/neutral coverage (10 articles)",
    "confidence": 0.5
  },
  "legislative": {
    "bills_introduced": 0,
    "bills_passed": 0,
    "private_member_bills": 0,
    "zero_hour_mentions": 0,
    "special_mentions": 0,
    "confidence": 0.0,
    "sources": []
  },
  "constituency_context": {
    "population": null,
    "literacy_rate": null,
    "urban_percentage": null,
    "district": ""
  },
  "voting_analysis": {
    "total_votes": 0,
    "votes_with_party": 0,
    "votes_against_party": 0,
    "abstentions": 0,
    "absences": 0,
    "party_loyalty_pct": null,
    "cross_party_votes": [],
    "key_bills_missed": [],
    "confidence": 0.0
  },
  "question_quality": {
    "total_questions": 0,
    "starred_questions": 0,
    "unstarred_questions": 0,
    "short_notice_questions": 0,
    "unique_topics": 0,
    "constituency_relevant": 0,
    "follow_up_rate": 0.0,
    "quality_score": 0.0,
    "confidence": 0.0
  },
  "conflict_of_interest": {
    "mp_businesses": [],
    "committee_sectors": [],
    "question_sectors": [],
    "overlaps": [],
    "severity": "none",
    "analysis_notes": "",
    "confidence": 0.0
  },
  "attendance_pattern": {
    "overall_pct": null,
    "session_breakdown": {},
    "consecutive_absences": 0,
    "attended_key_debates": true,
    "zero_hour_presence": null,
    "pattern_label": "",
    "confidence": 0.0
  },
  "mgnrega": {
    "employment_days_generated": null,
    "total_expenditure": null,
    "works_completed": null,
    "works_in_progress": null,
    "avg_wage_per_day": null,
    "financial_year": "",
    "confidence": 0.0,
    "sources": []
  },
  "pm_kisan": {
    "total_beneficiaries": null,
    "amount_disbursed": null,
    "installment_number": null,
    "financial_year": "",
    "confidence": 0.0,
    "sources": []
  }
}