{
  "mp": {
    "name": "Virendra Kumar",
    "constituency": "Tikamgarh",
    "state": "madhya pradesh",
    "party": "Bharatiya Janata Party",
    "myneta_candidate_id": null,
    "slug": "virendra-kumar",
    "house": "lok_sabha",
    "sansad_member_id": 515,
    "profile_url": null,
    "canonical_name": null,
    "name_aliases": [],
    "education": null,
    "profession": null,
    "age": null,
    "photo_url": null
  },
  "findings": {
    "mp": {
      "name": "Virendra Kumar",
      "constituency": "Tikamgarh",
      "state": "madhya pradesh",
      "party": "Bharatiya Janata Party",
      "myneta_candidate_id": null,
      "slug": "virendra-kumar",
      "house": "lok_sabha",
      "sansad_member_id": 515,
      "profile_url": null,
      "canonical_name": null,
      "name_aliases": [],
      "education": null,
      "profession": null,
      "age": null,
      "photo_url": null
    },
    "criminal_record": {
      "total_cases": 0,
      "serious_cases": 0,
      "convictions": 0,
      "pending_cases": 0,
      "disposed_cases": 0,
      "cases": [],
      "source": "myneta",
      "confidence": 0.0,
      "sources": []
    },
    "assets": {
      "movable_assets": null,
      "immovable_assets": null,
      "total_assets": null,
      "liabilities": null,
      "net_worth": null,
      "previous_total_assets": null,
      "asset_year": null,
      "previous_asset_year": null,
      "source": "myneta",
      "confidence": 0.0,
      "sources": [],
      "annual_income": null,
      "election_expenditure": null,
      "wealth_percentile": null,
      "growth_ratio": null
    },
    "mplads": {
      "entitled": null,
      "released": null,
      "sanctioned": null,
      "expended": null,
      "source": "mplads",
      "confidence": 0.0,
      "sources": [
        {
          "url": "https://mplads.mospi.gov.in",
          "source_name": "esakshi",
          "grade": "A",
          "fetched_at": "2026-05-21T14:32:10.615983Z",
          "notes": "eSAKSHI data not available — all fetch strategies failed"
        },
        {
          "url": "https://api.data.gov.in/resource/9e0e3220-3de0-4f10-924b-eca88a58b272",
          "source_name": "data.gov.in",
          "grade": "B",
          "fetched_at": "2026-05-21T14:31:08.684962Z",
          "notes": "MPLADS dataset resource ID no longer valid on data.gov.in (returns 'Meta not found')"
        },
        {
          "url": "https://dataful.in/datasets/18540/",
          "source_name": "mplads_csv",
          "grade": "E",
          "fetched_at": "2026-05-21T14:31:08.682039Z",
          "notes": "MPLADS data unavailable — dataset covers 12th-16th Lok Sabha only"
        }
      ],
      "works": [],
      "works_count": 0,
      "esakshi_coverage_start": null,
      "period_data": [],
      "cumulative_entitled": null,
      "cumulative_released": null,
      "cumulative_expended": null,
      "includes_covid_suspension": false,
      "data_period_note": "Constituency-level MPLADS figures for the 18th Lok Sabha are not published in a consistently accessible machine-readable source at this time. The legacy MoSPI/data.gov.in dataset covers older Lok Sabha terms and the eSAKSHI portal is treated as unavailable unless a per-constituency record is positively matched. This profile therefore marks MPLADS as unavailable rather than estimating fund amounts. Use the RTI template below for constituency-level verification.",
      "utilization_rate": null
    },
    "parliament_activity": {
      "attendance_percentage": null,
      "questions_asked": 0,
      "debates_participated": 0,
      "private_bills_introduced": 0,
      "is_minister": true,
      "source": "prs",
      "confidence": 0.3,
      "sources": [
        {
          "url": "https://raw.githubusercontent.com/Vonter/india-representatives-activity/main/csv/Lok%20Sabha/18th.csv",
          "source_name": "prs_github_csv",
          "grade": "C",
          "fetched_at": "2026-05-21T14:31:08.680897Z",
          "notes": "PRS India GitHub CSV - 18th Lok Sabha"
        }
      ],
      "focus_topics": [],
      "notable_questions": [],
      "voting_record": []
    },
    "news_allegations": [],
    "raw_notes": "",
    "sources_consulted": [
      "prs",
      "social_media",
      "news"
    ],
    "collected_at": "2026-05-21T14:32:10.616114Z",
    "evidence_summary": {
      "parliament": "C",
      "accessibility": "D"
    },
    "cag_findings": [
      {
        "report_title": "Performance Audit of MPLADS",
        "report_number": "31 of 2010",
        "year": 2010,
        "finding": "Idle funds: Rs 1,558 crore lying unspent in district authorities' accounts across states",
        "category": "idle_funds",
        "state": "national",
        "severity": "high",
        "source": {
          "url": "https://cag.gov.in/en/audit-report/details/2341",
          "source_name": "cag",
          "grade": "A",
          "fetched_at": "2026-05-21T14:32:10.631293Z",
          "notes": "CAG Report No. 31 of 2010"
        }
      },
      {
        "report_title": "Performance Audit of MPLADS",
        "report_number": "31 of 2010",
        "year": 2010,
        "finding": "Bogus utilization certificates: 34% of sampled UCs lacked proper supporting documents",
        "category": "bogus_ucs",
        "state": "national",
        "severity": "high",
        "source": {
          "url": "https://cag.gov.in/en/audit-report/details/2341",
          "source_name": "cag",
          "grade": "A",
          "fetched_at": "2026-05-21T14:32:10.631314Z",
          "notes": "CAG Report No. 31 of 2010"
        }
      },
      {
        "report_title": "Performance Audit of MPLADS",
        "report_number": "31 of 2010",
        "year": 2010,
        "finding": "Incomplete works: 18% of sampled works were abandoned or incomplete",
        "category": "incomplete_works",
        "state": "national",
        "severity": "medium",
        "source": {
          "url": "https://cag.gov.in/en/audit-report/details/2341",
          "source_name": "cag",
          "grade": "A",
          "fetched_at": "2026-05-21T14:32:10.631322Z",
          "notes": "CAG Report No. 31 of 2010"
        }
      },
      {
        "report_title": "Follow-up Audit of MPLADS",
        "report_number": "9 of 2013",
        "year": 2013,
        "finding": "Persistent idle funds: District authorities retained Rs 2,100 crore in unspent balances",
        "category": "idle_funds",
        "state": "national",
        "severity": "high",
        "source": {
          "url": "https://cag.gov.in/uploads/media/Follow-up-action-on-Audit-Report-20200902114923.pdf",
          "source_name": "cag",
          "grade": "A",
          "fetched_at": "2026-05-21T14:32:10.631330Z",
          "notes": "CAG Report No. 9 of 2013"
        }
      },
      {
        "report_title": "Follow-up Audit of MPLADS",
        "report_number": "9 of 2013",
        "year": 2013,
        "finding": "Works executed outside MP constituency in multiple states",
        "category": "irregular_works",
        "state": "madhya pradesh",
        "severity": "medium",
        "source": {
          "url": "https://cag.gov.in/uploads/media/Follow-up-action-on-Audit-Report-20200902114923.pdf",
          "source_name": "cag",
          "grade": "A",
          "fetched_at": "2026-05-21T14:32:10.631349Z",
          "notes": "CAG Report No. 9 of 2013"
        }
      },
      {
        "report_title": "Performance Audit of MPLADS (2012-17)",
        "report_number": "CAG Performance Report 2017",
        "year": 2017,
        "finding": "Only 53% of recommended works completed within the audit period",
        "category": "incomplete_works",
        "state": "national",
        "severity": "medium",
        "source": {
          "url": "https://www.mplads.gov.in/MPLADS/UploadedFiles/cag%20performance%20report.pdf",
          "source_name": "cag",
          "grade": "A",
          "fetched_at": "2026-05-21T14:32:10.631357Z",
          "notes": "CAG Report No. CAG Performance Report 2017"
        }
      },
      {
        "report_title": "Performance Audit of MPLADS (2012-17)",
        "report_number": "CAG Performance Report 2017",
        "year": 2017,
        "finding": "Rs 293 crore expended on inadmissible works not covered under MPLADS guidelines",
        "category": "irregular_works",
        "state": "national",
        "severity": "high",
        "source": {
          "url": "https://www.mplads.gov.in/MPLADS/UploadedFiles/cag%20performance%20report.pdf",
          "source_name": "cag",
          "grade": "A",
          "fetched_at": "2026-05-21T14:32:10.631363Z",
          "notes": "CAG Report No. CAG Performance Report 2017"
        }
      },
      {
        "report_title": "Performance Audit of MPLADS (2012-17)",
        "report_number": "CAG Performance Report 2017",
        "year": 2017,
        "finding": "Asset registers not maintained by district authorities in 40% of sampled districts",
        "category": "poor_records",
        "state": "national",
        "severity": "medium",
        "source": {
          "url": "https://www.mplads.gov.in/MPLADS/UploadedFiles/cag%20performance%20report.pdf",
          "source_name": "cag",
          "grade": "A",
          "fetched_at": "2026-05-21T14:32:10.631370Z",
          "notes": "CAG Report No. CAG Performance Report 2017"
        }
      }
    ],
    "compensation": {
      "salary_per_month": 100000.0,
      "constituency_allowance_per_month": 70000.0,
      "office_expense_allowance_per_month": 60000.0,
      "sumptuary_allowance_per_month": 15000.0,
      "total_monthly": 245000.0,
      "total_annual": 2940000.0,
      "effective_from": "2018-04-01",
      "source_notification": "Members of Parliament (Amendment) Act, 2018; The Salary, Allowances and Pension of Members of Parliament Act, 1954 (as amended). Gazette of India, Extraordinary, Part II, Section 1.",
      "notes": "In addition to cash compensation, MPs receive non-cash perks including: free AC First Class rail travel, 34 annual air journeys, furnished office space, medical facilities at government hospitals, and housing or HRA (Rs 2,00,000/month if no government accommodation). Post-retirement pension: Rs 29,000/month (base) + Rs 1,500 per additional year served."
    },
    "sagy": [],
    "committees": {
      "memberships": [],
      "total_committees": 0,
      "leadership_roles": 0,
      "confidence": 0.0,
      "sources": []
    },
    "social_media": {
      "profiles": [],
      "total_platforms": 0,
      "total_followers": 0,
      "confidence": 0.2,
      "sources": []
    },
    "news_sentiment": {
      "total_articles": 10,
      "positive": 0,
      "negative": 0,
      "neutral": 10,
      "top_headlines": [
        {
          "headline": "Dalit Veteran Virendra Kumar Sworn In As Union Minister In Modi 3.0 Cabinet - NDTV",
          "source": "NDTV",
          "severity": "low",
          "verified": false,
          "url": "https://news.google.com/rss/articles/CBMitgFBVV95cUxOZ2JicE1nWFR5RXk4Z1V6NTZWZUFkTVV0NXJFOUtReXE0d1EzQmZFT0xfQXhuQ1N6N0t1RGhiZWVSYXZWem5UTmFWMGNGcktGQzhDOVJySWM4Vk1FMnEtLTJ0OXRfQWRnZDIxeFUySnBLVzZTbHB2azRxTng2SUpfeERWbU5HaVhONUgxTGxXWDhZODkxM1VkTWRnWVJaWDBQUDItamNqaHlFSl9YZ3JzdFVUQkRid9IBvgFBVV95cUxQTDZOZzYwQ29aQ0F5ZnBkbUdoZlJ2OHUtSnlZdElMSmZ1dnpRVVhNbkZHcHdGY1BIWWREUXZ5OXZUMnBWSDNvYVhfb1JZQ19qZlRjbHZYZFI2THhsSi1RV29CeVE4Yl9FU1paanJ4Tm5OSzl2c0JsNFN0YXhMS1Y3SWoxZ2xZVHY2cmNmc3E0bEEtTUxoemIza2xKOXNRREsxNS1PS1RDMW9RLXY4S0tXUzVYNy1GYjRjbll4MEd3?oc=5",
          "sentiment": "neutral"
        },
        {
          "headline": "Virendra Kumar Khatik: कभी पंचर बनाते थे ये केंद्रीय मंत्री, आज भी अपने पुराने स्कूटर की वजह से बटोरते हैं चर्चा - AajTak",
          "source": "AajTak",
          "severity": "low",
          "verified": false,
          "url": "https://news.google.com/rss/articles/CBMi0gFBVV95cUxOZTMxcktSTEVOQzZPeFNvUVoyVmN0NWRjUmhHSTF5NE9NVEpsQmI2Mmd3cHJ3QUxKV0ZvOWpGcEJIYjYtS3NNSkc1Q1FHNVdWTDM1T1hhTTBsaFpsN3FPRFFBNTFENGtQZ1JYLUVjUFpxTzJzVHJlSG13V1oyc1hJRFJmamFnVnp4a2wzcTRwRmNJTHMwSWZyNGRPSzVnOTRybnZWNnE0cGNJdGg3QWJhbWRRNk9iWWwwanJ5V25DMm5DVDRGMEk2R0gwWEZ3VkxzV3fSAdcBQVVfeXFMTjJUSng1TVlXakdtcmZaTzQ0TkNjM3BtZGlwVEx4azZ3anRVN1ZZb183bzlwTDlhc1F6NVltTk84MTRqeXl5cHRBRDJEenpIN0pPMkdrRXZrMW9ybzZxOUhIaGhaSkR4enNkVlZXeU5pME1HenNlekJSTURJaWFXS05uSVFDOHJYNC15Z0h3cXJXbGdKb3I3a3Jad0RqbnBISi1ILTU2TmRrUzlLUjNjZHFuOWJ2YXoxb1FodFZoWU90emVfVGhyMTdpa2hPZEVYVEJoZ25uUFU?oc=5",
          "sentiment": "neutral"
        },
        {
          "headline": "BJP MP Virendra Kumar to be Protem speaker of Lok Sabha - The Hindu",
          "source": "The Hindu",
          "severity": "low",
          "verified": false,
          "url": "https://news.google.com/rss/articles/CBMitgFBVV95cUxQMTNiZEc4Um4xNEJvNFdZLUVpay13ZVZOMHlBQ2hVdUxTcWtpQjlBcUVTNFllUmhWTWNmZmFZM294dzVEdm9sNUExNkxaXzlzS3dzelUyQzBNdlBKX0QydkRyY1pHeWJ6QXRpU01YTzYxZE9iQkstVHRPX2dFMFZCX3dBVV9zVEJ4Y0IyaE5aTFE1V3Rjb3Z1SzFYcThGME42LXVGMW54MDl2U0NEZlFlNzdBeTRvZ9IBvAFBVV95cUxPR0s2Z2RGV2ozQWVKdzdpc3JlT0lRczNDX01WSnpOYVBMMTNuXy1weldwc2lVcDN5RDBwaE9ZRTU5MmpDZG9XZTZfSW12Z0hQZkViUnVCVWRQUUFDRW1PRzB4U0EzZENYSlJBN3d2eDVNTzFPRGtaSXlDQjRWdXowdEd5NHN4eE5RYWJBM0l4cjVEaGxUenRvN1p6SlN6eWlJZFc0ejRzOHdzRlRsWkE4QU4xeHFNam1uOER1cQ?oc=5",
          "sentiment": "neutral"
        },
        {
          "headline": "BJP minister Virendra Kumar bans touching feet at his office: ‘No work will be entertained’ - Mint",
          "source": "Mint",
          "severity": "low",
          "verified": false,
          "url": "https://news.google.com/rss/articles/CBMi4AFBVV95cUxPUDY1dEFUQVBjS0NtOWNJRGR3NUlNMy1NN2xpTXJCdTlOaTdmcDNsYXFpSk5HaEV0anpianU0N0R2TkhhUERoSEpCMUU3ZHFGRjRPSmZPS2s5S2hZcmVJMGR6RjJjU2tJSUcwNmRYSXo2bTlsVjVHMGVmWWxWWDhjaFZXN0VDejZMTXRFY1d5V0EzQU11My1EWHl2b3YwdjgycGp4OHduRGZvRGgxLUNyTHB0dnd0SDFHVFBUUnEzcHJDTFZhTVlvanM3ei1FemVCZU5DdktuMFlfdlpBblJCadIB5gFBVV95cUxNeUQzRldxaDBHNFYxMDRyc0JvM0FScGlNbmdibWNmSFlJb0tqVG5ydUZ3Q21UbEJmQ3psM05vQ0dpel9zbWpJaHBaQWFwbDJUb0Vtd0lqRVVDbXp0R3N0U0Jjd1ozSzZwTGtSNlRxZmtiYmJiSkx2LU9SWl9Ba1ZTbXJzTjByUzVKUnM2aVpUUlJkQ1BjQUZEWWlybUY1NXBXYWlBMzlXR2hTV25yaTFwUDcyYlZET0tnejUyZTFqSEZxYXppS1ZrS2JLQjhjaUVTdENFOHJ0SXhtSEdUZE1ORGUtWkIwQQ?oc=5",
          "sentiment": "neutral"
        },
        {
          "headline": "Touch feet, forget work: Minister's unique rule at his Madhya Pradesh office - India Today",
          "source": "India Today",
          "severity": "low",
          "verified": false,
          "url": "https://news.google.com/rss/articles/CBMi5AFBVV95cUxOZ29mbGItb1B4WG1EWExwLTZ4c3lCQ1pNZllLRFlzNXNBSnhKQXpTcUlMeTZxQXNfS1VDbHdDZ1pDaU5WekpnajFVNnBPa1I1ZUNhajZXMUEwa3ExNGw5RnFvckk4TVpGVEZ5Ry1fdm42NEoxMVJRVm1tMXUxSENTcThTWEI4RlhTR0lvMnY3OGdIQ1B4d0xGRUdhaTdvSTZDYUpTRlRzcjVoOWJqdzNkOWlzVnVWdXk4VFMyUVpZSkplMUxzaTdYY0FSdE1JUTlGQVBZQjRQOVk0N2JaaDRqRkN1V1TSAeoBQVVfeXFMTkdVbHlUTkE4U3pNR1NVTnpUdjl0NGRqTFY3cmZkMk9zaTdYOVBkdWhCYmJrM1RQMWRDSDlvcTVzSVNFc0Zza2F2cWp6Z3N3VkNvMXM5SGIwdXczZE8yTHl1RFdOLTRCbnpkdlZhV213U21Fc0xUTWduQ1QyMzd5NTZZQl9jMzNDcXZQWEFoOHhrOC1oMVVEWGVoa2RRNHdNNVA1YjZCQXNRcGtvbWp4SWI0WlpDZFBmV2JGUW5UUHRPMncweXUzbmlDTmtIUkZDUU1KTGo1anlrTXFRNjdjS2o1aTcyMzlHVlR3?oc=5",
          "sentiment": "neutral"
        }
      ],
      "sentiment_summary": "Mixed/neutral coverage (10 articles)",
      "confidence": 0.5
    },
    "legislative": {
      "bills_introduced": 0,
      "bills_passed": 0,
      "private_member_bills": 0,
      "zero_hour_mentions": 0,
      "special_mentions": 0,
      "confidence": 0.0,
      "sources": []
    },
    "constituency_context": {
      "population": null,
      "literacy_rate": null,
      "urban_percentage": null,
      "district": ""
    },
    "voting_analysis": {
      "total_votes": 0,
      "votes_with_party": 0,
      "votes_against_party": 0,
      "abstentions": 0,
      "absences": 0,
      "party_loyalty_pct": null,
      "cross_party_votes": [],
      "key_bills_missed": [],
      "confidence": 0.0
    },
    "question_quality": {
      "total_questions": 0,
      "starred_questions": 0,
      "unstarred_questions": 0,
      "short_notice_questions": 0,
      "unique_topics": 0,
      "constituency_relevant": 0,
      "follow_up_rate": 0.0,
      "quality_score": 0.0,
      "confidence": 0.0
    },
    "conflict_of_interest": {
      "mp_businesses": [],
      "committee_sectors": [],
      "question_sectors": [],
      "overlaps": [],
      "severity": "none",
      "analysis_notes": "",
      "confidence": 0.0
    },
    "attendance_pattern": {
      "overall_pct": null,
      "session_breakdown": {},
      "consecutive_absences": 0,
      "attended_key_debates": true,
      "zero_hour_presence": null,
      "pattern_label": "",
      "confidence": 0.0
    },
    "mgnrega": {
      "employment_days_generated": null,
      "total_expenditure": null,
      "works_completed": null,
      "works_in_progress": null,
      "avg_wage_per_day": null,
      "financial_year": "",
      "confidence": 0.0,
      "sources": []
    },
    "pm_kisan": {
      "total_beneficiaries": null,
      "amount_disbursed": null,
      "installment_number": null,
      "financial_year": "",
      "confidence": 0.0,
      "sources": []
    }
  },
  "overall_confidence": 0.07,
  "flags": [
    {
      "field": "criminal_record",
      "issue": "Low confidence in criminal data — source may be unavailable",
      "severity": "warning",
      "suggestion": ""
    },
    {
      "field": "assets",
      "issue": "Low confidence in asset data",
      "severity": "warning",
      "suggestion": ""
    },
    {
      "field": "mplads",
      "issue": "Low confidence in MPLADS data",
      "severity": "warning",
      "suggestion": ""
    },
    {
      "field": "parliament_activity",
      "issue": "Low confidence in parliament activity data",
      "severity": "warning",
      "suggestion": ""
    },
    {
      "field": "committees",
      "issue": "No committee data found — Sansad profile may be unavailable",
      "severity": "info",
      "suggestion": ""
    },
    {
      "field": "legislative",
      "issue": "Low confidence in legislative effectiveness data",
      "severity": "info",
      "suggestion": ""
    },
    {
      "field": "mplads",
      "issue": "CAG audit context for Madhya Pradesh: 8 relevant findings",
      "severity": "info",
      "suggestion": "[CAG 31 of 2010] Idle funds: Rs 1,558 crore lying unspent in district authorities' accounts across states; [CAG 31 of 2010] Bogus utilization certificates: 34% of sampled UCs lacked proper supporting documents; [CAG 31 of 2010] Incomplete works: 18% of sampled works were abandoned or incomplete"
    }
  ],
  "cross_reference_notes": "## Executive Summary: Virendra Kumar\n\n### Overall Assessment\nVirendra Kumar, BJP MP from Tikamgarh constituency in Madhya Pradesh, presents a mixed transparency profile with significant data gaps across multiple dimensions. While criminal records appear clean and news coverage remains neutral, the absence of critical financial and parliamentary performance data severely limits the ability to assess his effectiveness as a public representative. This analysis is hampered by low confidence ratings for most data categories.\n\n### Fund Utilization & Development\nNo MPLADS (Member of Parliament Local Area Development Scheme) data is available for assessment, including entitlement, release, expenditure, or utilization percentages. This represents a critical transparency gap given that MPLADS is a key mechanism for MPs to drive local development. The CAG audit context reveals systemic issues in Madhya Pradesh's fund management, including Rs 1,558 crore in idle funds lying unspent across district authorities and 34% of sampled utilization certificates lacking proper documentation. Additionally, 18% of sampled works were found to be abandoned or incomplete, raising concerns about development project execution in the state.\n\n### Financial Transparency\nAsset disclosure information is completely unavailable, with no data on total assets, previous assets, growth ratios, or net worth. This represents a significant transparency deficit as asset declarations are mandatory for all MPs and crucial for assessing potential conflicts of interest. The only available financial information is the monthly compensation of Rs 245,000, which aligns with standard parliamentary compensation structures. Without baseline asset data, it's impossible to track wealth accumulation or identify potential irregularities during tenure.\n\n### Legal & Criminal Standing\nVirendra Kumar maintains a clean legal record with zero criminal cases across all categories - no total cases, serious cases, pending cases, disposed cases, or convictions. However, this data carries a warning flag indicating low confidence due to potentially unavailable source information. While the clean record is positive, the data quality caveat suggests these findings should be interpreted cautiously.\n\n### Parliamentary Performance\nParliamentary activity data is entirely absent, with no information available on attendance rates, questions raised, participation in debates, or private bills introduced. Given that Kumar serves as a Minister, lower attendance might be expected due to executive responsibilities, but the complete absence of performance metrics prevents any meaningful assessment of his legislative effectiveness or constituency representation. This data gap is particularly concerning for accountability purposes.\n\n### Public Engagement & Accessibility\nMedia engagement shows moderate activity with 10 news articles identified, all classified as neutral in sentiment with no positive or negative coverage detected. This neutral media profile suggests limited controversial issues but may also indicate minimal public visibility or newsworthy activities. The evidence grade for accessibility is rated 'D', indicating poor performance in public engagement metrics. No social media or other accessibility data is available for comprehensive assessment.\n\n### Data Quality & Caveats\nThis analysis faces severe data quality limitations with multiple warning flags across core transparency areas. Parliament activity data receives a 'C' grade, while accessibility scores 'D'. Critical warnings include low confidence in criminal records, assets, MPLADS utilization, and parliamentary activity data. Additionally, no committee membership information is available, suggesting potential unavailability of the MP's Sansad profile. These data gaps significantly compromise the reliability of this transparency assessment.\n\n### Key Takeaway\nVirendra Kumar's transparency profile is severely compromised by widespread data unavailability across critical accountability metrics. While maintaining a clean legal record and neutral media coverage, the absence of financial disclosures, MPLADS utilization data, and parliamentary performance metrics raises significant transparency concerns. The systemic fund management issues identified in Madhya Pradesh's CAG audit context further underscore the importance of robust financial monitoring. Citizens and oversight bodies should prioritize obtaining complete disclosure information to enable proper accountability assessment of this MP's performance and conduct.",
  "validated_at": "2026-05-21T14:32:32.013858Z",
  "mplads": {
    "entitled": 14.7,
    "released": 14.7,
    "sanctioned": 8.3,
    "expended": 3.98,
    "source": "esakshi",
    "confidence": 0.9,
    "sources": [
      {
        "url": "https://mplads.mospi.gov.in/digigov/dashboard.html",
        "source_name": "esakshi",
        "grade": "A",
        "fetched_at": "2026-05-23T17:29:48.003657Z",
        "notes": "Official eSAKSHI REST API — Works: 247 recommended, 187 sanctioned, 6 completed"
      }
    ],
    "works": [],
    "works_count": 247,
    "esakshi_coverage_start": "2023-04-01",
    "period_data": [],
    "cumulative_entitled": null,
    "cumulative_released": null,
    "cumulative_expended": null,
    "includes_covid_suspension": false,
    "data_period_note": "",
    "utilization_rate": 27.074829931972786
  },
  "evidence_summary": {
    "mplads": "A"
  },
  "sources_consulted": [
    "mplads"
  ]
}