{
  "mp": {
    "name": "Pradeep Purohit",
    "constituency": "Bargarh",
    "state": "odisha",
    "party": "Bharatiya Janata Party",
    "myneta_candidate_id": 7148,
    "slug": "pradeep-purohit",
    "house": "lok_sabha",
    "sansad_member_id": 5668,
    "profile_url": null,
    "canonical_name": "Pradeep Purohit",
    "name_aliases": [],
    "education": "10th",
    "profession": null,
    "age": 58,
    "photo_url": "/mp-photos/5668.jpg"
  },
  "composite_score": 30.6,
  "breakdown": {
    "mplads_score": 8.3,
    "asset_score": 50.0,
    "criminal_score": 20.0,
    "attendance_score": 95.0,
    "participation_score": 80.0,
    "committee_score": 0.0,
    "accessibility_score": 10.0,
    "legislative_score": 0.0
  },
  "data_confidence": 0.5,
  "qualitative_assessment": "MP Pradeep Purohit shows a mixed transparency profile with strong attendance (95%) and clean criminal record, but significant gaps in committee participation, legislative contributions, and public accessibility. The moderate MPLADS and assets disclosure scores, combined with zero committee engagement, suggest limited comprehensive transparency despite good parliamentary attendance.",
  "key_finding": "Criminal cases noted, high attendance",
  "scored_at": "2026-05-21T14:27:16.510876Z",
  "raw": {
    "criminal_record": {
      "total_cases": 8,
      "serious_cases": 0,
      "pending_cases": 8,
      "convictions": 0,
      "disposed_cases": 0,
      "confidence": 0.8,
      "source": "myneta"
    },
    "assets": {
      "total_assets": 22595410.0,
      "liabilities": 676737.0,
      "movable_assets": 0,
      "immovable_assets": 0,
      "net_worth": 21918673.0,
      "confidence": 0.8,
      "source": "myneta"
    }
  }
}